dsvdd/__init__.py
dsvdd/datasets.py
dsvdd/deepSVDD.py
dsvdd/networks.py
dsvdd/utils.py
deep_svdd-1.3.dist-info/METADATA
deep_svdd-1.3.dist-info/WHEEL
deep_svdd-1.3.dist-info/top_level.txt
deep_svdd-1.3.dist-info/RECORD
