Metadata-Version: 2.1
Name: deep-svdd
Version: 1.3
Summary: Tensorflow implementation of Deep SVDD
Home-page: https://github.com/nuclearboy95/Deep-SVDD-Tensorflow
Author: Jihun Yi
Author-email: t080205@gmail.com
License: MIT
Platform: UNKNOWN
Requires-Dist: numpy
Requires-Dist: scikit-learn
Requires-Dist: tensorflow-gpu (>=1.12.0)
Requires-Dist: matplotlib
Requires-Dist: tqdm
